MANIFEST.in
README.md
setup.py
Slushbox.egg-info/PKG-INFO
Slushbox.egg-info/SOURCES.txt
Slushbox.egg-info/dependency_links.txt
Slushbox.egg-info/requires.txt
Slushbox.egg-info/top_level.txt
bin/slushbox
slushbox/__init__.py
slushbox/applescripts.py
slushbox/slushbox.py