Metadata-Version: 1.0
Name: Slushbox
Version: 0.1.2
Summary: Reloads local web pages when files in their directories         change.
Home-page: https://github.com/workmajj/slushbox
Author: John J. Workman
Author-email: workman@alumni.duke.edu
License: BSD 3-Clause <http://www.opensource.org/licenses/BSD-3-Clause>
Platform: UNKNOWN
Classifier: Development Status :: 3 - Alpha
Classifier: Operating System :: MacOS :: MacOS X
Classifier: Topic :: System :: Filesystems
Classifier: Topic :: Utilities
